{
    "annotations": {
      "list": [
        {
          "builtIn": 1,
          "datasource": "-- Grafana --",
          "enable": true,
          "hide": true,
          "iconColor": "rgba(0, 211, 255, 1)",
          "name": "Annotations & Alerts",
          "type": "dashboard"
        }
      ]
    },
    "description": "Performance metrics for Nginx",
    "editable": true,
    "gnetId": 5063,
    "graphTooltip": 0,
    "id": 9,
    "links": [],
    "panels": [
      {
        "collapsed": false,
        "datasource": null,
        "gridPos": {
          "h": 1,
          "w": 24,
          "x": 0,
          "y": 0
        },
        "id": 12,
        "panels": [],
        "repeat": "host",
        "title": "System",
        "type": "row"
      },
      {
        "cacheTimeout": null,
        "colorBackground": false,
        "colorValue": false,
        "colors": [
          "rgba(245, 54, 54, 0.9)",
          "rgba(237, 129, 40, 0.89)",
          "rgba(50, 172, 45, 0.97)"
        ],
        "datasource": "InfluxDB",
        "decimals": 1,
        "editable": true,
        "error": false,
        "fieldConfig": {
          "defaults": {
            "custom": {}
          },
          "overrides": []
        },
        "format": "ns",
        "gauge": {
          "maxValue": 100,
          "minValue": 0,
          "show": false,
          "thresholdLabels": false,
          "thresholdMarkers": true
        },
        "gridPos": {
          "h": 3,
          "w": 6,
          "x": 0,
          "y": 1
        },
        "height": "55px",
        "id": 1,
        "interval": null,
        "isNew": true,
        "links": [],
        "mappingType": 1,
        "mappingTypes": [
          {
            "name": "value to text",
            "value": 1
          },
          {
            "name": "range to text",
            "value": 2
          }
        ],
        "maxDataPoints": 100,
        "nullPointMode": "connected",
        "nullText": null,
        "postfix": "s",
        "postfixFontSize": "80%",
        "prefix": "",
        "prefixFontSize": "50%",
        "rangeMaps": [
          {
            "from": "null",
            "text": "N/A",
            "to": "null"
          }
        ],
        "sparkline": {
          "fillColor": "rgba(31, 118, 189, 0.18)",
          "full": false,
          "lineColor": "rgb(31, 120, 193)",
          "show": false
        },
        "tableColumn": "",
        "targets": [
          {
            "groupBy": [
              {
                "params": [
                  "$__interval"
                ],
                "type": "time"
              },
              {
                "params": [
                  "null"
                ],
                "type": "fill"
              }
            ],
            "measurement": "docker_container_status",
            "orderByTime": "ASC",
            "policy": "default",
            "refId": "A",
            "resultFormat": "time_series",
            "select": [
              [
                {
                  "params": [
                    "uptime_ns"
                  ],
                  "type": "field"
                },
                {
                  "params": [],
                  "type": "mean"
                }
              ]
            ],
            "tags": [
              {
                "key": "com.docker.swarm.service.name",
                "operator": "=",
                "value": "app_webserver"
              }
            ]
          }
        ],
        "thresholds": "",
        "title": "Uptime",
        "type": "singlestat",
        "valueFontSize": "80%",
        "valueMaps": [
          {
            "op": "=",
            "text": "N/A",
            "value": "null"
          }
        ],
        "valueName": "avg"
      },
      {
        "cacheTimeout": null,
        "colorBackground": false,
        "colorValue": false,
        "colors": [
          "rgba(245, 54, 54, 0.9)",
          "rgba(237, 129, 40, 0.89)",
          "rgba(50, 172, 45, 0.97)"
        ],
        "datasource": "InfluxDB",
        "editable": true,
        "error": false,
        "fieldConfig": {
          "defaults": {
            "custom": {}
          },
          "overrides": []
        },
        "format": "percent",
        "gauge": {
          "maxValue": 100,
          "minValue": 0,
          "show": false,
          "thresholdLabels": false,
          "thresholdMarkers": true
        },
        "gridPos": {
          "h": 3,
          "w": 6,
          "x": 6,
          "y": 1
        },
        "height": "55px",
        "id": 2,
        "interval": null,
        "isNew": true,
        "links": [],
        "mappingType": 1,
        "mappingTypes": [
          {
            "name": "value to text",
            "value": 1
          },
          {
            "name": "range to text",
            "value": 2
          }
        ],
        "maxDataPoints": 100,
        "nullPointMode": "connected",
        "nullText": null,
        "postfix": "",
        "postfixFontSize": "50%",
        "prefix": "",
        "prefixFontSize": "50%",
        "rangeMaps": [
          {
            "from": "null",
            "text": "N/A",
            "to": "null"
          }
        ],
        "sparkline": {
          "fillColor": "rgba(31, 118, 189, 0.18)",
          "full": false,
          "lineColor": "rgb(31, 120, 193)",
          "show": false
        },
        "tableColumn": "",
        "targets": [
          {
            "groupBy": [
              {
                "params": [
                  "$__interval"
                ],
                "type": "time"
              },
              {
                "params": [
                  "null"
                ],
                "type": "fill"
              }
            ],
            "measurement": "docker_container_cpu",
            "orderByTime": "ASC",
            "policy": "default",
            "refId": "A",
            "resultFormat": "time_series",
            "select": [
              [
                {
                  "params": [
                    "usage_percent"
                  ],
                  "type": "field"
                },
                {
                  "params": [],
                  "type": "mean"
                }
              ]
            ],
            "tags": [
              {
                "key": "com.docker.swarm.service.name",
                "operator": "=",
                "value": "app_webserver"
              }
            ]
          }
        ],
        "thresholds": "",
        "title": "CPUs",
        "type": "singlestat",
        "valueFontSize": "80%",
        "valueMaps": [
          {
            "op": "=",
            "text": "N/A",
            "value": "null"
          }
        ],
        "valueName": "avg"
      },
      {
        "cacheTimeout": null,
        "colorBackground": false,
        "colorValue": false,
        "colors": [
          "rgba(245, 54, 54, 0.9)",
          "rgba(237, 129, 40, 0.89)",
          "rgba(50, 172, 45, 0.97)"
        ],
        "datasource": "InfluxDB",
        "decimals": 0,
        "editable": true,
        "error": false,
        "fieldConfig": {
          "defaults": {
            "custom": {}
          },
          "overrides": []
        },
        "format": "bytes",
        "gauge": {
          "maxValue": 100,
          "minValue": 0,
          "show": false,
          "thresholdLabels": false,
          "thresholdMarkers": true
        },
        "gridPos": {
          "h": 3,
          "w": 6,
          "x": 12,
          "y": 1
        },
        "height": "55px",
        "id": 3,
        "interval": null,
        "isNew": true,
        "links": [],
        "mappingType": 1,
        "mappingTypes": [
          {
            "name": "value to text",
            "value": 1
          },
          {
            "name": "range to text",
            "value": 2
          }
        ],
        "maxDataPoints": 100,
        "nullPointMode": "connected",
        "nullText": null,
        "postfix": "",
        "postfixFontSize": "50%",
        "prefix": "",
        "prefixFontSize": "50%",
        "rangeMaps": [
          {
            "from": "null",
            "text": "N/A",
            "to": "null"
          }
        ],
        "sparkline": {
          "fillColor": "rgba(31, 118, 189, 0.18)",
          "full": false,
          "lineColor": "rgb(31, 120, 193)",
          "show": false
        },
        "tableColumn": "",
        "targets": [
          {
            "groupBy": [
              {
                "params": [
                  "$__interval"
                ],
                "type": "time"
              },
              {
                "params": [
                  "null"
                ],
                "type": "fill"
              }
            ],
            "measurement": "docker_container_mem",
            "orderByTime": "ASC",
            "policy": "default",
            "refId": "A",
            "resultFormat": "time_series",
            "select": [
              [
                {
                  "params": [
                    "usage"
                  ],
                  "type": "field"
                },
                {
                  "params": [],
                  "type": "mean"
                }
              ]
            ],
            "tags": [
              {
                "key": "com.docker.swarm.service.name",
                "operator": "=",
                "value": "app_webserver"
              }
            ]
          }
        ],
        "thresholds": "",
        "title": "RAM",
        "type": "singlestat",
        "valueFontSize": "80%",
        "valueMaps": [
          {
            "op": "=",
            "text": "N/A",
            "value": "null"
          }
        ],
        "valueName": "avg"
      },
      {
        "cacheTimeout": null,
        "colorBackground": false,
        "colorValue": false,
        "colors": [
          "rgba(245, 54, 54, 0.9)",
          "rgba(237, 129, 40, 0.89)",
          "rgba(50, 172, 45, 0.97)"
        ],
        "datasource": "InfluxDB",
        "editable": true,
        "error": false,
        "fieldConfig": {
          "defaults": {
            "custom": {}
          },
          "overrides": []
        },
        "format": "none",
        "gauge": {
          "maxValue": 100,
          "minValue": 0,
          "show": false,
          "thresholdLabels": false,
          "thresholdMarkers": true
        },
        "gridPos": {
          "h": 3,
          "w": 6,
          "x": 18,
          "y": 1
        },
        "height": "55px",
        "id": 4,
        "interval": null,
        "isNew": true,
        "links": [],
        "mappingType": 1,
        "mappingTypes": [
          {
            "name": "value to text",
            "value": 1
          },
          {
            "name": "range to text",
            "value": 2
          }
        ],
        "maxDataPoints": 100,
        "nullPointMode": "connected",
        "nullText": null,
        "postfix": "%",
        "postfixFontSize": "80%",
        "prefix": "",
        "prefixFontSize": "50%",
        "rangeMaps": [
          {
            "from": "null",
            "text": "N/A",
            "to": "null"
          }
        ],
        "sparkline": {
          "fillColor": "rgba(31, 118, 189, 0.18)",
          "full": true,
          "lineColor": "rgb(31, 120, 193)",
          "show": true
        },
        "tableColumn": "",
        "targets": [
          {
            "groupBy": [
              {
                "params": [
                  "$__interval"
                ],
                "type": "time"
              },
              {
                "params": [
                  "null"
                ],
                "type": "fill"
              }
            ],
            "measurement": "docker_container_mem",
            "orderByTime": "ASC",
            "policy": "default",
            "refId": "A",
            "resultFormat": "time_series",
            "select": [
              [
                {
                  "params": [
                    "usage_percent"
                  ],
                  "type": "field"
                },
                {
                  "params": [],
                  "type": "mean"
                }
              ]
            ],
            "tags": [
              {
                "key": "com.docker.swarm.service.name",
                "operator": "=",
                "value": "app_webserver"
              }
            ]
          }
        ],
        "thresholds": "",
        "title": "Memory Used",
        "type": "singlestat",
        "valueFontSize": "80%",
        "valueMaps": [
          {
            "op": "=",
            "text": "N/A",
            "value": "null"
          }
        ],
        "valueName": "avg"
      },
      {
        "aliasColors": {},
        "bars": false,
        "dashLength": 10,
        "dashes": false,
        "datasource": "InfluxDB",
        "fieldConfig": {
          "defaults": {
            "custom": {},
            "links": []
          },
          "overrides": []
        },
        "fill": 1,
        "fillGradient": 0,
        "gridPos": {
          "h": 8,
          "w": 12,
          "x": 0,
          "y": 4
        },
        "hiddenSeries": false,
        "id": 29,
        "legend": {
          "alignAsTable": true,
          "avg": true,
          "current": true,
          "max": true,
          "min": false,
          "rightSide": false,
          "show": true,
          "total": true,
          "values": true
        },
        "lines": true,
        "linewidth": 1,
        "links": [],
        "nullPointMode": "null",
        "percentage": false,
        "pluginVersion": "7.1.0",
        "pointradius": 5,
        "points": false,
        "renderer": "flot",
        "seriesOverrides": [
          {
            "alias": "tx",
            "transform": "negative-Y"
          }
        ],
        "spaceLength": 10,
        "stack": false,
        "steppedLine": false,
        "targets": [
          {
            "alias": "rx",
            "groupBy": [
              {
                "params": [
                  "$__interval"
                ],
                "type": "time"
              },
              {
                "params": [
                  "null"
                ],
                "type": "fill"
              }
            ],
            "measurement": "docker_container_net",
            "orderByTime": "ASC",
            "policy": "default",
            "refId": "A",
            "resultFormat": "time_series",
            "select": [
              [
                {
                  "params": [
                    "rx_bytes"
                  ],
                  "type": "field"
                },
                {
                  "params": [],
                  "type": "mean"
                },
                {
                  "params": [
                    "10s"
                  ],
                  "type": "derivative"
                }
              ]
            ],
            "tags": [
              {
                "key": "com.docker.swarm.service.name",
                "operator": "=",
                "value": "app_webserver"
              }
            ]
          },
          {
            "alias": "tx",
            "groupBy": [
              {
                "params": [
                  "$__interval"
                ],
                "type": "time"
              },
              {
                "params": [
                  "null"
                ],
                "type": "fill"
              }
            ],
            "measurement": "docker_container_net",
            "orderByTime": "ASC",
            "policy": "default",
            "refId": "B",
            "resultFormat": "time_series",
            "select": [
              [
                {
                  "params": [
                    "tx_bytes"
                  ],
                  "type": "field"
                },
                {
                  "params": [],
                  "type": "mean"
                },
                {
                  "params": [
                    "10s"
                  ],
                  "type": "derivative"
                }
              ]
            ],
            "tags": [
              {
                "key": "com.docker.swarm.service.name",
                "operator": "=",
                "value": "app_webserver"
              }
            ]
          }
        ],
        "thresholds": [],
        "timeFrom": null,
        "timeRegions": [],
        "timeShift": null,
        "title": "bytes",
        "tooltip": {
          "shared": true,
          "sort": 0,
          "value_type": "individual"
        },
        "type": "graph",
        "xaxis": {
          "buckets": null,
          "mode": "time",
          "name": null,
          "show": true,
          "values": []
        },
        "yaxes": [
          {
            "format": "bytes",
            "label": null,
            "logBase": 1,
            "max": null,
            "min": null,
            "show": true
          },
          {
            "format": "short",
            "label": null,
            "logBase": 1,
            "max": null,
            "min": null,
            "show": true
          }
        ],
        "yaxis": {
          "align": false,
          "alignLevel": null
        }
      },
      {
        "aliasColors": {},
        "bars": true,
        "dashLength": 10,
        "dashes": false,
        "datasource": "InfluxDB",
        "fieldConfig": {
          "defaults": {
            "custom": {},
            "links": []
          },
          "overrides": []
        },
        "fill": 1,
        "fillGradient": 1,
        "gridPos": {
          "h": 8,
          "w": 12,
          "x": 12,
          "y": 4
        },
        "hiddenSeries": false,
        "id": 33,
        "legend": {
          "alignAsTable": true,
          "avg": true,
          "current": true,
          "max": false,
          "min": false,
          "rightSide": true,
          "show": true,
          "total": true,
          "values": true
        },
        "lines": true,
        "linewidth": 1,
        "links": [],
        "nullPointMode": "connected",
        "percentage": false,
        "pluginVersion": "7.1.0",
        "pointradius": 1,
        "points": false,
        "renderer": "flot",
        "seriesOverrides": [
          {
            "alias": "tx pack",
            "transform": "negative-Y"
          },
          {
            "alias": "tx drop",
            "transform": "negative-Y"
          },
          {
            "alias": "tx err",
            "transform": "negative-Y"
          }
        ],
        "spaceLength": 10,
        "stack": false,
        "steppedLine": true,
        "targets": [
          {
            "alias": "rx drop",
            "groupBy": [
              {
                "params": [
                  "$__interval"
                ],
                "type": "time"
              },
              {
                "params": [
                  "null"
                ],
                "type": "fill"
              }
            ],
            "measurement": "docker_container_net",
            "orderByTime": "ASC",
            "policy": "default",
            "refId": "A",
            "resultFormat": "time_series",
            "select": [
              [
                {
                  "params": [
                    "rx_dropped"
                  ],
                  "type": "field"
                },
                {
                  "params": [],
                  "type": "mean"
                },
                {
                  "params": [
                    "10s"
                  ],
                  "type": "derivative"
                }
              ]
            ],
            "tags": [
              {
                "key": "com.docker.swarm.service.name",
                "operator": "=",
                "value": "app_webserver"
              }
            ]
          },
          {
            "alias": "rx err",
            "groupBy": [
              {
                "params": [
                  "$__interval"
                ],
                "type": "time"
              },
              {
                "params": [
                  "null"
                ],
                "type": "fill"
              }
            ],
            "measurement": "docker_container_net",
            "orderByTime": "ASC",
            "policy": "default",
            "refId": "B",
            "resultFormat": "time_series",
            "select": [
              [
                {
                  "params": [
                    "rx_errors"
                  ],
                  "type": "field"
                },
                {
                  "params": [],
                  "type": "mean"
                },
                {
                  "params": [
                    "10s"
                  ],
                  "type": "derivative"
                }
              ]
            ],
            "tags": [
              {
                "key": "com.docker.swarm.service.name",
                "operator": "=",
                "value": "app_webserver"
              }
            ]
          },
          {
            "alias": "rx pack",
            "groupBy": [
              {
                "params": [
                  "$__interval"
                ],
                "type": "time"
              },
              {
                "params": [
                  "null"
                ],
                "type": "fill"
              }
            ],
            "measurement": "docker_container_net",
            "orderByTime": "ASC",
            "policy": "default",
            "refId": "C",
            "resultFormat": "time_series",
            "select": [
              [
                {
                  "params": [
                    "rx_packets"
                  ],
                  "type": "field"
                },
                {
                  "params": [],
                  "type": "mean"
                },
                {
                  "params": [
                    "10s"
                  ],
                  "type": "derivative"
                }
              ]
            ],
            "tags": [
              {
                "key": "com.docker.swarm.service.name",
                "operator": "=",
                "value": "app_webserver"
              }
            ]
          },
          {
            "alias": "tx drop",
            "groupBy": [
              {
                "params": [
                  "$__interval"
                ],
                "type": "time"
              },
              {
                "params": [
                  "null"
                ],
                "type": "fill"
              }
            ],
            "measurement": "docker_container_net",
            "orderByTime": "ASC",
            "policy": "default",
            "refId": "D",
            "resultFormat": "time_series",
            "select": [
              [
                {
                  "params": [
                    "tx_dropped"
                  ],
                  "type": "field"
                },
                {
                  "params": [],
                  "type": "mean"
                },
                {
                  "params": [
                    "10s"
                  ],
                  "type": "derivative"
                }
              ]
            ],
            "tags": [
              {
                "key": "com.docker.swarm.service.name",
                "operator": "=",
                "value": "app_webserver"
              }
            ]
          },
          {
            "alias": "tx err",
            "groupBy": [
              {
                "params": [
                  "$__interval"
                ],
                "type": "time"
              },
              {
                "params": [
                  "null"
                ],
                "type": "fill"
              }
            ],
            "measurement": "docker_container_net",
            "orderByTime": "ASC",
            "policy": "default",
            "refId": "E",
            "resultFormat": "time_series",
            "select": [
              [
                {
                  "params": [
                    "tx_errors"
                  ],
                  "type": "field"
                },
                {
                  "params": [],
                  "type": "mean"
                },
                {
                  "params": [
                    "10s"
                  ],
                  "type": "derivative"
                }
              ]
            ],
            "tags": [
              {
                "key": "com.docker.swarm.service.name",
                "operator": "=",
                "value": "app_webserver"
              }
            ]
          },
          {
            "alias": "tx pack",
            "groupBy": [
              {
                "params": [
                  "$__interval"
                ],
                "type": "time"
              },
              {
                "params": [
                  "null"
                ],
                "type": "fill"
              }
            ],
            "measurement": "docker_container_net",
            "orderByTime": "ASC",
            "policy": "default",
            "refId": "F",
            "resultFormat": "time_series",
            "select": [
              [
                {
                  "params": [
                    "tx_packets"
                  ],
                  "type": "field"
                },
                {
                  "params": [],
                  "type": "mean"
                },
                {
                  "params": [
                    "10s"
                  ],
                  "type": "derivative"
                }
              ]
            ],
            "tags": [
              {
                "key": "com.docker.swarm.service.name",
                "operator": "=",
                "value": "app_webserver"
              }
            ]
          }
        ],
        "thresholds": [],
        "timeFrom": null,
        "timeRegions": [],
        "timeShift": null,
        "title": "packets",
        "tooltip": {
          "shared": true,
          "sort": 0,
          "value_type": "individual"
        },
        "type": "graph",
        "xaxis": {
          "buckets": null,
          "mode": "time",
          "name": null,
          "show": true,
          "values": []
        },
        "yaxes": [
          {
            "format": "none",
            "label": null,
            "logBase": 1,
            "max": null,
            "min": null,
            "show": true
          },
          {
            "format": "short",
            "label": null,
            "logBase": 1,
            "max": null,
            "min": null,
            "show": true
          }
        ],
        "yaxis": {
          "align": false,
          "alignLevel": null
        }
      },
      {
        "collapsed": false,
        "datasource": null,
        "gridPos": {
          "h": 1,
          "w": 24,
          "x": 0,
          "y": 12
        },
        "id": 13,
        "panels": [],
        "repeat": "host",
        "title": "Nginx",
        "type": "row"
      },
      {
        "aliasColors": {},
        "bars": true,
        "dashLength": 10,
        "dashes": false,
        "datasource": "InfluxDB",
        "fieldConfig": {
          "defaults": {
            "custom": {},
            "links": []
          },
          "overrides": []
        },
        "fill": 1,
        "fillGradient": 1,
        "gridPos": {
          "h": 9,
          "w": 24,
          "x": 0,
          "y": 13
        },
        "hiddenSeries": false,
        "id": 31,
        "legend": {
          "alignAsTable": true,
          "avg": true,
          "current": true,
          "hideEmpty": true,
          "hideZero": true,
          "max": false,
          "min": false,
          "rightSide": true,
          "show": true,
          "total": true,
          "values": true
        },
        "lines": false,
        "linewidth": 1,
        "links": [],
        "nullPointMode": "null",
        "percentage": false,
        "pluginVersion": "7.1.0",
        "pointradius": 3,
        "points": true,
        "renderer": "flot",
        "seriesOverrides": [],
        "spaceLength": 10,
        "stack": false,
        "steppedLine": false,
        "targets": [
          {
            "alias": "HTTP 1xx",
            "groupBy": [
              {
                "params": [
                  "$__interval"
                ],
                "type": "time"
              }
            ],
            "measurement": "logparser",
            "orderByTime": "ASC",
            "policy": "default",
            "refId": "B",
            "resultFormat": "time_series",
            "select": [
              [
                {
                  "params": [
                    "resp_bytes"
                  ],
                  "type": "field"
                },
                {
                  "params": [],
                  "type": "mean"
                }
              ]
            ],
            "tags": [
              {
                "key": "resp_code",
                "operator": "=~",
                "value": "/^1/"
              }
            ]
          },
          {
            "alias": "HTTP 2xx",
            "groupBy": [
              {
                "params": [
                  "$__interval"
                ],
                "type": "time"
              }
            ],
            "measurement": "logparser",
            "orderByTime": "ASC",
            "policy": "default",
            "refId": "A",
            "resultFormat": "time_series",
            "select": [
              [
                {
                  "params": [
                    "resp_bytes"
                  ],
                  "type": "field"
                },
                {
                  "params": [],
                  "type": "mean"
                }
              ]
            ],
            "tags": [
              {
                "key": "resp_code",
                "operator": "=~",
                "value": "/^2/"
              }
            ]
          },
          {
            "alias": "HTTP 3xx",
            "groupBy": [
              {
                "params": [
                  "$__interval"
                ],
                "type": "time"
              }
            ],
            "measurement": "logparser",
            "orderByTime": "ASC",
            "policy": "default",
            "refId": "C",
            "resultFormat": "time_series",
            "select": [
              [
                {
                  "params": [
                    "resp_bytes"
                  ],
                  "type": "field"
                },
                {
                  "params": [],
                  "type": "mean"
                }
              ]
            ],
            "tags": [
              {
                "key": "resp_code",
                "operator": "=~",
                "value": "/^3/"
              }
            ]
          },
          {
            "alias": "HTTP 4xx",
            "groupBy": [
              {
                "params": [
                  "$__interval"
                ],
                "type": "time"
              }
            ],
            "measurement": "logparser",
            "orderByTime": "ASC",
            "policy": "default",
            "refId": "D",
            "resultFormat": "time_series",
            "select": [
              [
                {
                  "params": [
                    "resp_bytes"
                  ],
                  "type": "field"
                },
                {
                  "params": [],
                  "type": "mean"
                }
              ]
            ],
            "tags": [
              {
                "key": "resp_code",
                "operator": "=~",
                "value": "/^4/"
              }
            ]
          },
          {
            "alias": "HTTP 5xx",
            "groupBy": [
              {
                "params": [
                  "$__interval"
                ],
                "type": "time"
              }
            ],
            "measurement": "logparser",
            "orderByTime": "ASC",
            "policy": "default",
            "refId": "E",
            "resultFormat": "time_series",
            "select": [
              [
                {
                  "params": [
                    "resp_bytes"
                  ],
                  "type": "field"
                },
                {
                  "params": [],
                  "type": "mean"
                }
              ]
            ],
            "tags": [
              {
                "key": "resp_code",
                "operator": "=~",
                "value": "/^5/"
              }
            ]
          }
        ],
        "thresholds": [],
        "timeFrom": null,
        "timeRegions": [],
        "timeShift": null,
        "title": "HTTP",
        "tooltip": {
          "shared": true,
          "sort": 0,
          "value_type": "individual"
        },
        "type": "graph",
        "xaxis": {
          "buckets": null,
          "mode": "time",
          "name": null,
          "show": true,
          "values": []
        },
        "yaxes": [
          {
            "format": "decbytes",
            "label": null,
            "logBase": 1,
            "max": null,
            "min": null,
            "show": true
          },
          {
            "format": "short",
            "label": null,
            "logBase": 1,
            "max": null,
            "min": null,
            "show": true
          }
        ],
        "yaxis": {
          "align": false,
          "alignLevel": null
        }
      },
      {
        "datasource": "InfluxDB",
        "fieldConfig": {
          "defaults": {
            "custom": {
              "align": null
            },
            "mappings": [],
            "thresholds": {
              "mode": "absolute",
              "steps": [
                {
                  "color": "green",
                  "value": null
                },
                {
                  "color": "red",
                  "value": 90
                }
              ]
            }
          },
          "overrides": []
        },
        "gridPos": {
          "h": 5,
          "w": 12,
          "x": 0,
          "y": 22
        },
        "id": 32,
        "links": [],
        "options": {
          "displayMode": "lcd",
          "orientation": "horizontal",
          "reduceOptions": {
            "calcs": [
              "sum"
            ],
            "fields": "",
            "values": false
          },
          "showUnfilled": true
        },
        "pluginVersion": "7.1.0",
        "targets": [
          {
            "alias": "$tag_verb",
            "groupBy": [
              {
                "params": [
                  "$__interval"
                ],
                "type": "time"
              },
              {
                "params": [
                  "verb"
                ],
                "type": "tag"
              }
            ],
            "measurement": "logparser",
            "orderByTime": "ASC",
            "policy": "default",
            "query": "SELECT mean(\"resp_bytes\") FROM \"nginx_access_log\" WHERE (\"host\" =~ /^$host$/) AND $timeFilter GROUP BY time($__interval), \"host\", \"resp_code\" fill(null) SLIMIT 10",
            "rawQuery": false,
            "refId": "B",
            "resultFormat": "time_series",
            "select": [
              [
                {
                  "params": [
                    "request"
                  ],
                  "type": "field"
                },
                {
                  "params": [],
                  "type": "count"
                }
              ]
            ],
            "slimit": "",
            "tags": [
              {
                "key": "verb",
                "operator": "=",
                "value": "POST"
              }
            ]
          },
          {
            "alias": "$tag_verb",
            "groupBy": [
              {
                "params": [
                  "$__interval"
                ],
                "type": "time"
              },
              {
                "params": [
                  "verb"
                ],
                "type": "tag"
              }
            ],
            "measurement": "logparser",
            "orderByTime": "ASC",
            "policy": "default",
            "refId": "C",
            "resultFormat": "time_series",
            "select": [
              [
                {
                  "params": [
                    "request"
                  ],
                  "type": "field"
                },
                {
                  "params": [],
                  "type": "count"
                }
              ]
            ],
            "tags": [
              {
                "key": "verb",
                "operator": "=",
                "value": "GET"
              }
            ]
          }
        ],
        "timeFrom": null,
        "timeShift": null,
        "title": "Queries",
        "type": "bargauge"
      },
      {
        "datasource": "InfluxDB",
        "fieldConfig": {
          "defaults": {
            "custom": {
              "align": null
            },
            "mappings": [],
            "thresholds": {
              "mode": "absolute",
              "steps": [
                {
                  "color": "semi-dark-blue",
                  "value": null
                }
              ]
            },
            "unit": "none"
          },
          "overrides": []
        },
        "gridPos": {
          "h": 5,
          "w": 12,
          "x": 12,
          "y": 22
        },
        "id": 34,
        "links": [],
        "options": {
          "colorMode": "background",
          "graphMode": "area",
          "justifyMode": "center",
          "orientation": "horizontal",
          "reduceOptions": {
            "calcs": [
              "sum"
            ],
            "fields": "",
            "values": false
          },
          "textMode": "auto"
        },
        "pluginVersion": "7.1.0",
        "repeat": "datasource",
        "repeatDirection": "h",
        "targets": [
          {
            "alias": "grafana",
            "groupBy": [
              {
                "params": [
                  "$__interval"
                ],
                "type": "time"
              },
              {
                "params": [
                  "path"
                ],
                "type": "tag"
              }
            ],
            "measurement": "logparser",
            "orderByTime": "ASC",
            "policy": "default",
            "query": "SELECT last(\"client_ip\")  FROM \"logparser\" WHERE (\"path\" = '/var/log/nginx/nginx_m_access.log') AND $timeFilter GROUP BY time($__interval)",
            "rawQuery": false,
            "refId": "B",
            "resultFormat": "time_series",
            "select": [
              [
                {
                  "params": [
                    "request"
                  ],
                  "type": "field"
                },
                {
                  "params": [],
                  "type": "count"
                }
              ]
            ],
            "slimit": "",
            "tags": [
              {
                "key": "path",
                "operator": "=",
                "value": "/var/log/nginx/graf_access.log"
              }
            ]
          },
          {
            "alias": "portainer",
            "groupBy": [
              {
                "params": [
                  "$__interval"
                ],
                "type": "time"
              },
              {
                "params": [
                  "path"
                ],
                "type": "tag"
              }
            ],
            "measurement": "logparser",
            "orderByTime": "ASC",
            "policy": "default",
            "query": "SELECT last(\"client_ip\")  FROM \"logparser\" WHERE (\"path\" = '/var/log/nginx/nginx_m_access.log') AND $timeFilter GROUP BY time($__interval)",
            "rawQuery": false,
            "refId": "A",
            "resultFormat": "time_series",
            "select": [
              [
                {
                  "params": [
                    "request"
                  ],
                  "type": "field"
                },
                {
                  "params": [],
                  "type": "count"
                }
              ]
            ],
            "slimit": "",
            "tags": [
              {
                "key": "path",
                "operator": "=",
                "value": "/var/log/nginx/port_access.log"
              }
            ]
          }
        ],
        "timeFrom": null,
        "timeShift": null,
        "title": "Queries",
        "type": "stat"
      },
      {
        "aliasColors": {},
        "bars": false,
        "dashLength": 10,
        "dashes": false,
        "datasource": "InfluxDB",
        "decimals": 0,
        "editable": true,
        "error": false,
        "fieldConfig": {
          "defaults": {
            "custom": {},
            "links": []
          },
          "overrides": []
        },
        "fill": 1,
        "fillGradient": 0,
        "grid": {},
        "gridPos": {
          "h": 8,
          "w": 24,
          "x": 0,
          "y": 27
        },
        "hiddenSeries": false,
        "id": 8,
        "isNew": true,
        "legend": {
          "alignAsTable": true,
          "avg": true,
          "current": true,
          "max": true,
          "min": false,
          "rightSide": true,
          "show": true,
          "total": true,
          "values": true
        },
        "lines": true,
        "linewidth": 1,
        "links": [],
        "nullPointMode": "connected",
        "percentage": false,
        "pluginVersion": "7.1.0",
        "pointradius": 5,
        "points": false,
        "renderer": "flot",
        "seriesOverrides": [],
        "spaceLength": 10,
        "stack": false,
        "steppedLine": false,
        "targets": [
          {
            "alias": "",
            "dsType": "influxdb",
            "groupBy": [
              {
                "params": [
                  "$interval"
                ],
                "type": "time"
              },
              {
                "params": [
                  "null"
                ],
                "type": "fill"
              }
            ],
            "measurement": "nginx",
            "orderByTime": "ASC",
            "policy": "default",
            "refId": "A",
            "resultFormat": "time_series",
            "select": [
              [
                {
                  "params": [
                    "accepts"
                  ],
                  "type": "field"
                },
                {
                  "params": [],
                  "type": "mean"
                },
                {
                  "params": [
                    "10s"
                  ],
                  "type": "non_negative_derivative"
                },
                {
                  "params": [
                    "accepts"
                  ],
                  "type": "alias"
                }
              ],
              [
                {
                  "params": [
                    "active"
                  ],
                  "type": "field"
                },
                {
                  "params": [],
                  "type": "mean"
                },
                {
                  "params": [
                    "10s"
                  ],
                  "type": "non_negative_derivative"
                },
                {
                  "params": [
                    "active"
                  ],
                  "type": "alias"
                }
              ],
              [
                {
                  "params": [
                    "handled"
                  ],
                  "type": "field"
                },
                {
                  "params": [],
                  "type": "mean"
                },
                {
                  "params": [
                    "10s"
                  ],
                  "type": "non_negative_derivative"
                },
                {
                  "params": [
                    "handled"
                  ],
                  "type": "alias"
                }
              ],
              [
                {
                  "params": [
                    "reading"
                  ],
                  "type": "field"
                },
                {
                  "params": [],
                  "type": "mean"
                },
                {
                  "params": [
                    "10s"
                  ],
                  "type": "non_negative_derivative"
                },
                {
                  "params": [
                    "reading"
                  ],
                  "type": "alias"
                }
              ],
              [
                {
                  "params": [
                    "requests"
                  ],
                  "type": "field"
                },
                {
                  "params": [],
                  "type": "mean"
                },
                {
                  "params": [
                    "10s"
                  ],
                  "type": "non_negative_derivative"
                },
                {
                  "params": [
                    "requests"
                  ],
                  "type": "alias"
                }
              ],
              [
                {
                  "params": [
                    "waiting"
                  ],
                  "type": "field"
                },
                {
                  "params": [],
                  "type": "mean"
                },
                {
                  "params": [
                    "10s"
                  ],
                  "type": "non_negative_derivative"
                },
                {
                  "params": [
                    "waiting"
                  ],
                  "type": "alias"
                }
              ],
              [
                {
                  "params": [
                    "writing"
                  ],
                  "type": "field"
                },
                {
                  "params": [],
                  "type": "mean"
                },
                {
                  "params": [
                    "10s"
                  ],
                  "type": "non_negative_derivative"
                },
                {
                  "params": [
                    "writing"
                  ],
                  "type": "alias"
                }
              ]
            ],
            "tags": [
              {
                "key": "port",
                "operator": "=",
                "value": "8066"
              }
            ]
          }
        ],
        "thresholds": [],
        "timeFrom": null,
        "timeRegions": [],
        "timeShift": null,
        "title": "Workers",
        "tooltip": {
          "msResolution": false,
          "shared": true,
          "sort": 0,
          "value_type": "cumulative"
        },
        "type": "graph",
        "xaxis": {
          "buckets": null,
          "mode": "time",
          "name": null,
          "show": true,
          "values": []
        },
        "yaxes": [
          {
            "format": "short",
            "label": null,
            "logBase": 1,
            "max": null,
            "min": null,
            "show": true
          },
          {
            "format": "short",
            "label": null,
            "logBase": 1,
            "max": null,
            "min": null,
            "show": true
          }
        ],
        "yaxis": {
          "align": false,
          "alignLevel": null
        }
      }
    ],
    "refresh": "30s",
    "schemaVersion": 26,
    "style": "dark",
    "tags": [
      "Nginx",
      "InfluxDB",
      "Telegraf"
    ],
    "templating": {
      "list": []
    },
    "time": {
      "from": "now-1h",
      "to": "now"
    },
    "timepicker": {
      "nowDelay": "",
      "refresh_intervals": [
        "10s",
        "30s",
        "1m",
        "5m",
        "15m",
        "30m",
        "1h",
        "2h",
        "1d"
      ],
      "time_options": [
        "5m",
        "15m",
        "1h",
        "6h",
        "12h",
        "24h",
        "2d",
        "7d",
        "30d"
      ]
    },
    "timezone": "browser",
    "title": "Nginx-INF",
    "uid": "GqFjuAgmk",
    "version": 167
  }